pylingo/__init__.py
pylingo/__main__.py
pylingo/pyVisitor.py
pylingo/pylingoLexer.py
pylingo/pylingoListener.py
pylingo/pylingoParser.py
pylingo/pylingoVisitor.py
pylingo-0.0.5.dist-info/LICENSE
pylingo-0.0.5.dist-info/METADATA
pylingo-0.0.5.dist-info/WHEEL
pylingo-0.0.5.dist-info/top_level.txt
pylingo-0.0.5.dist-info/RECORD
