Metadata-Version: 2.1
Name: pylingo
Version: 0.0.5
Summary: General Purpose Configuration Language Framework
Home-page: https://github.com/dialectsoftware/pylingo
Author: Dialect Software LLC
Author-email: support@dialectsoftware.com
License: UNKNOWN
Platform: UNKNOWN
Classifier: Programming Language :: Python :: 3.6
Classifier: License :: OSI Approved :: MIT License
Classifier: Operating System :: OS Independent
Requires-Dist: antlr4-python3-runtime
